pypertext/__init__.py
pypertext/bootstrap.py
pypertext/hypertext.py
pypertext-0.1.6.dist-info/licenses/LICENSE
pypertext-0.1.6.dist-info/METADATA
pypertext-0.1.6.dist-info/WHEEL
pypertext-0.1.6.dist-info/top_level.txt
pypertext-0.1.6.dist-info/RECORD
