Metadata-Version: 2.4
Name: pypertext
Version: 0.1.6
Summary: Pythonic HTML
Author: Asif Rahman
License: Apache License 2.0
Keywords: HTML,Web Development
Classifier: Programming Language :: Python :: 3.9
Classifier: Programming Language :: Python :: 3.10
Classifier: Programming Language :: Python :: 3.11
Classifier: Programming Language :: Python :: 3.12
Classifier: Operating System :: OS Independent
Classifier: Environment :: Web Environment
Classifier: Topic :: Internet :: WWW/HTTP
Requires-Python: >=3.9
License-File: LICENSE
Requires-Dist: importlib-metadata; python_version < "3.10"
Requires-Dist: typing-extensions
Provides-Extra: dev
Requires-Dist: ruff; extra == "dev"
Requires-Dist: ipykernel; extra == "dev"
Requires-Dist: pytest; extra == "dev"
Requires-Dist: pytest-cov; extra == "dev"
Requires-Dist: nbformat; extra == "dev"
Dynamic: license-file
